Workbook
Name aporte: 'JF Investimentos'!$D$16
Name patrimonio: 'JF Investimentos'!$D$19
Name qtd_anos: 'JF Investimentos'!$D$17
Name rendimento_carteira: 'JF Investimentos'!$D$11
Name salario: 'JF Investimentos'!$D$10
Name sugestao_investimento: 'JF Investimentos'!$D$12
Name taxa_mensal: 'JF Investimentos'!$D$18

Sheet JF Investimentos
B9: CONFIGURAÇÕES | F9: PERFIL DE INVESTIMENTO
B10: Salário | D10: 5000 | F10: Selecione seu Perfil | H10: Conservador
B11: Rendimento Carteira | D11: 0.006 | F11: VALOR A SER INVESTIDO POR MÊS | H11: 500
B12: Sugestão de Investimento | D12: =salario*30% -> 1500
F13: TIPO DE FII | G13: Percentual Sugerido | H13: Valores
B14: INVESTIMENTO MENSAL | F14: PAPEL | G14: =VLOOKUP($H$10&"-"&$F14,Perfis!A:D,4,FALSE) -> 0.3 | H14: =$H$11*G14 -> 150
F15: TIJOLO | G15: =VLOOKUP($H$10&"-"&$F15,Perfis!A:D,4,FALSE) -> 0.5 | H15: =$H$11*G15 -> 250
B16: Quanto investir por mês? | D16: 500 | F16: HÍBRIDOS | G16: =VLOOKUP($H$10&"-"&$F16,Perfis!A:D,4,FALSE) -> 0.1 | H16: =$H$11*G16 -> 50
B17: Por quantos anos? | D17: 5 | F17: FOFs | G17: =VLOOKUP($H$10&"-"&$F17,Perfis!A:D,4,FALSE) -> 0.1 | H17: =$H$11*G17 -> 50
B18: Taxa de rendimento mensal? | D18: 0.01079 | F18: DESENVOLVIMENTO | G18: =VLOOKUP($H$10&"-"&$F18,Perfis!A:D,4,FALSE) -> 0 | H18: =$H$11*G18 -> 0
B19: Patrimônio acumulado? | D19: =FV(taxa_mensal,qtd_anos*12,-aporte) -> 41888.457 | F19: HOTELARIAS | G19: =VLOOKUP($H$10&"-"&$F19,Perfis!A:D,4,FALSE) -> 0 | H19: =$H$11*G19 -> 0
B20: Dividendos mensais? | D20: =patrimonio*rendimento_carteira -> 251.33074 | F20: =SUM(H14:H19) -> 500
B22: CENÁRIOS
B23: Tempo | C23: Total | D23: Dividendo
A24: 2 | B24: Quanto em 2 anos? | C24: =FV(taxa_mensal,A24*12,-aporte) -> 13613.814 | D24: =C24*rendimento_carteira -> 81.682882
A25: 5 | B25: Quanto em 5 anos? | C25: =FV(taxa_mensal,A25*12,-aporte) -> 41888.457 | D25: =C25*rendimento_carteira -> 251.33074
A26: 10 | B26: Quanto em 10 anos? | C26: =FV(taxa_mensal,A26*12,-aporte) -> 121642.11 | D26: =C26*rendimento_carteira -> 729.85264
A27: 20 | B27: Quanto em 20 anos? | C27: =FV(taxa_mensal,A27*12,-aporte) -> 562599.2 | D27: =C27*rendimento_carteira -> 3375.5952
A28: 30 | B28: Quanto em 30 anos? | C28: =FV(taxa_mensal,A28*12,-aporte) -> 2161084.8 | D28: =C28*rendimento_carteira -> 12966.509

Sheet Perfis
A2: CHAVE | B2: PERFIL | C2: TIPO DE FII | D2: %
A3: =B3&"-"&C3 -> Conservador-PAPEL | B3: Conservador | C3: PAPEL | D3: 0.3
A4: =B4&"-"&C4 -> Conservador-TIJOLO | B4: Conservador | C4: TIJOLO | D4: 0.5
A5: =B5&"-"&C5 -> Conservador-HÍBRIDOS | B5: Conservador | C5: HÍBRIDOS | D5: 0.1
A6: =B6&"-"&C6 -> Conservador-FOFs | B6: Conservador | C6: FOFs | D6: 0.1
A7: =B7&"-"&C7 -> Conservador-DESENVOLVIMENTO | B7: Conservador | C7: DESENVOLVIMENTO | D7: 0
A8: =B8&"-"&C8 -> Conservador-HOTELARIAS | B8: Conservador | C8: HOTELARIAS | D8: 0
A9: =B9&"-"&C9 -> Moderado-PAPEL | B9: Moderado | C9: PAPEL | D9: 0.32
A10: =B10&"-"&C10 -> Moderado-TIJOLO | B10: Moderado | C10: TIJOLO | D10: 0.35
A11: =B11&"-"&C11 -> Moderado-HÍBRIDOS | B11: Moderado | C11: HÍBRIDOS | D11: 0.05
A12: =B12&"-"&C12 -> Moderado-FOFs | B12: Moderado | C12: FOFs | D12: 0.1
A13: =B13&"-"&C13 -> Moderado-DESENVOLVIMENTO | B13: Moderado | C13: DESENVOLVIMENTO | D13: 0.1
A14: =B14&"-"&C14 -> Moderado-HOTELARIAS | B14: Moderado | C14: HOTELARIAS | D14: 0.1
... A20: =B20&"-"&C20 -> Agressivo-HOTELARIAS | B20: Agressivo | C20: HOTELARIAS | D20: 0.1
